dataschool/__init__.py
dataschool/class_test_gen.py
dataschool/clustering.py
dataschool/json_parser.py
dataschool/matrix_creation.py
dataschool/question_correlation.py
dataschool/statistic_viewer.py
dataschool-0.2.0.dist-info/AUTHORS.rst
dataschool-0.2.0.dist-info/LICENSE
dataschool-0.2.0.dist-info/METADATA
dataschool-0.2.0.dist-info/WHEEL
dataschool-0.2.0.dist-info/top_level.txt
dataschool-0.2.0.dist-info/RECORD
