Metadata-Version: 2.1
Name: dataschool
Version: 0.2.0
Summary: Full kit to analyse datas (data transformation, clustering, graphs)
Home-page: https://github.com/ulysse-qd/dataschool
Author: Ulysse Queritet-Diop
Author-email: ulysse-q@evidenceb.com
License: MIT license
Keywords: dataschool
Platform: UNKNOWN
Classifier: Development Status :: 2 - Pre-Alpha
Classifier: Intended Audience :: Developers
Classifier: License :: OSI Approved :: MIT License
Classifier: Natural Language :: English
Classifier: Programming Language :: Python :: 3
Classifier: Programming Language :: Python :: 3.5
Classifier: Programming Language :: Python :: 3.6
Classifier: Programming Language :: Python :: 3.7
Classifier: Programming Language :: Python :: 3.8
Requires-Python: >=3.5
Requires-Dist: scikit-learn
Requires-Dist: matplotlib
Requires-Dist: wheel
Requires-Dist: pandas
Requires-Dist: numpy
Requires-Dist: seaborn
Requires-Dist: scipy
Requires-Dist: isodate
Requires-Dist: networkx
